{"pipes":[],"interfaces":[],"injectables":[],"classes":[],"modules":[{"name":"LyTypographyModule","children":[{"type":"providers","elements":[]},{"type":"declarations","elements":[{"name":"LyTypography"}]},{"type":"imports","elements":[]},{"type":"exports","elements":[{"name":"LyTypography"}]},{"type":"bootstrap","elements":[]},{"type":"classes","elements":[]}]}],"miscellaneous":{"variables":[{"name":"STYLE_PRIORITY","ctype":"miscellaneous","subtype":"variable","file":"src/lib/typography/typography.directive.ts","type":"","defaultValue":"-2"},{"name":"styles","ctype":"miscellaneous","subtype":"variable","file":"src/lib/typography/typography.directive.ts","type":"","defaultValue":"({\n  root: {\n    margin: 0,\n    display: 'block'\n  }\n})"}],"functions":[],"typealiases":[],"enumerations":[{"name":"Gutter","childs":[{"name":"default"},{"name":"top"},{"name":"bottom"}],"ctype":"miscellaneous","subtype":"enum","description":"","file":"src/lib/typography/typography.directive.ts"}],"groupedVariables":{"src/lib/typography/typography.directive.ts":[{"name":"STYLE_PRIORITY","ctype":"miscellaneous","subtype":"variable","file":"src/lib/typography/typography.directive.ts","type":"","defaultValue":"-2"},{"name":"styles","ctype":"miscellaneous","subtype":"variable","file":"src/lib/typography/typography.directive.ts","type":"","defaultValue":"({\n  root: {\n    margin: 0,\n    display: 'block'\n  }\n})"}]},"groupedFunctions":{},"groupedEnumerations":{"src/lib/typography/typography.directive.ts":[{"name":"Gutter","childs":[{"name":"default"},{"name":"top"},{"name":"bottom"}],"ctype":"miscellaneous","subtype":"enum","description":"","file":"src/lib/typography/typography.directive.ts"}]},"groupedTypeAliases":{}},"routes":[],"coverage":{},"c_d":[{"title":"directives","data":[{"name":"LyTypography","id":"directive-LyTypography-9eb6981ccce32945e8a1e9688fc4e322","file":"src/lib/typography/typography.directive.ts","type":"directive","description":"","selector":"[lyTyp]","providers":[],"inputsClass":[{"name":"gutter","line":46,"type":"boolean"},{"name":"gutterBottom","line":71,"type":"boolean"},{"name":"gutterTop","line":58,"type":"boolean"},{"name":"lyTyp","line":36,"type":"string"}],"outputsClass":[],"hostBindings":[],"hostListeners":[],"propertiesClass":[{"name":"classes","defaultValue":"this.style.addStyleSheet(styles, 'lyTyp', STYLE_PRIORITY)","type":"","optional":false,"description":"","line":22}],"methodsClass":[],"implements":["OnInit"],"accessors":{"lyTyp":{"name":"lyTyp","setSignature":{"name":"lyTyp","type":"void","args":[{"name":"val","type":"string"}],"returnType":"void","line":36,"jsdoctags":[{"name":"val","type":"string","tagName":{"text":"param"}}]},"getSignature":{"name":"lyTyp","type":"","returnType":"","line":41}},"gutter":{"name":"gutter","setSignature":{"name":"gutter","type":"void","args":[{"name":"val","type":"boolean"}],"returnType":"void","line":46,"jsdoctags":[{"name":"val","type":"boolean","tagName":{"text":"param"}}]},"getSignature":{"name":"gutter","type":"","returnType":"","line":53}},"gutterTop":{"name":"gutterTop","setSignature":{"name":"gutterTop","type":"void","args":[{"name":"val","type":"boolean"}],"returnType":"void","line":58,"jsdoctags":[{"name":"val","type":"boolean","tagName":{"text":"param"}}]},"getSignature":{"name":"gutterTop","type":"","returnType":"","line":66}},"gutterBottom":{"name":"gutterBottom","setSignature":{"name":"gutterBottom","type":"void","args":[{"name":"val","type":"boolean"}],"returnType":"void","line":71,"jsdoctags":[{"name":"val","type":"boolean","tagName":{"text":"param"}}]},"getSignature":{"name":"gutterBottom","type":"","returnType":"","line":78}}}}]}]}